phot2lc/__init__.py
phot2lc/config.dat
phot2lc/photfunc.py
phot2lc/teledat.py
phot2lc/ucm_utils.py
phot2lc/version_history.txt
phot2lc-1.8.1.data/scripts/addstar
phot2lc-1.8.1.data/scripts/phot2lc
phot2lc-1.8.1.data/scripts/photconfig
phot2lc-1.8.1.data/scripts/quicklook
phot2lc-1.8.1.data/scripts/weldlc
phot2lc-1.8.1.dist-info/LICENSE
phot2lc-1.8.1.dist-info/METADATA
phot2lc-1.8.1.dist-info/WHEEL
phot2lc-1.8.1.dist-info/top_level.txt
phot2lc-1.8.1.dist-info/RECORD
