Metadata-Version: 2.1
Name: phot2lc
Version: 1.8.1
Summary: Light curve extraction
Home-page: https://github.com/zvanderbosch/phot2lc
Author: Zach Vanderbosch
Author-email: zvanderbosch@gmail.com
Classifier: Development Status :: 3 - Alpha
Classifier: Intended Audience :: Science/Research
Classifier: Topic :: Scientific/Engineering :: Astronomy
Classifier: Programming Language :: Python :: 3
Classifier: License :: OSI Approved :: MIT License
Classifier: Operating System :: OS Independent
Requires-Python: >=3.6
License-File: LICENSE
